torchtree_physher/__init__.py
torchtree_physher/_version.py
torchtree_physher/branch_model.py
torchtree_physher/coalescent.py
torchtree_physher/ctmc_scale.py
torchtree_physher/data_type.py
torchtree_physher/interface.py
torchtree_physher/physher.cpython-312-darwin.so
torchtree_physher/site_model.py
torchtree_physher/substitution_model.py
torchtree_physher/tree_likelihood.py
torchtree_physher/tree_model.py
torchtree_physher/utils.py
torchtree_physher/cli/__init__.py
torchtree_physher-1.0.0.dist-info/LICENSE
torchtree_physher-1.0.0.dist-info/METADATA
torchtree_physher-1.0.0.dist-info/WHEEL
torchtree_physher-1.0.0.dist-info/top_level.txt
torchtree_physher-1.0.0.dist-info/RECORD
