Metadata-Version: 2.1
Name: torchtree-physher
Version: 1.0.0
Summary: Phylogenetic inference with pytorch and physher
Home-page: https://github.com/4ment/torchtree-physher
Author: Mathieu Fourment
Author-email: mathieu.fourment@uts.edu.au
License: GPL3
Keywords: phylogenetics,variational,Bayes,pytorch
Classifier: Intended Audience :: Science/Research
Classifier: License :: OSI Approved :: GNU General Public License v3 (GPLv3)
Classifier: Operating System :: OS Independent
Classifier: Programming Language :: Python :: 3.7
Classifier: Programming Language :: Python :: 3.8
Classifier: Programming Language :: Python :: 3.9
Classifier: Programming Language :: Python :: 3.10
Classifier: Topic :: Scientific/Engineering :: Bio-Informatics
Requires-Python: >=3.7
License-File: LICENSE
Requires-Dist: dendropy
Requires-Dist: numpy >=1.7
Requires-Dist: torch >=1.9
Requires-Dist: torchtree
Provides-Extra: dev
Requires-Dist: black ; extra == 'dev'
Requires-Dist: cpplint ; extra == 'dev'
Requires-Dist: flake8 ; extra == 'dev'
Requires-Dist: isort ; extra == 'dev'
Requires-Dist: pylint ; extra == 'dev'
Provides-Extra: test
Requires-Dist: pytest ; extra == 'test'
